<?xml version="1.0" encoding="UTF-8"?>

<!DOCTYPE mapper
	PUBLIC "-//mybatis.org//DTD Mapper 3.0//EN"
	"http://mybatis.org/dtd/mybatis-3-mapper.dtd">

<mapper namespace="com.playhere.couple.ICoupleCodeService">

  <select id="findByUserId" parameterType="String" resultType="com.playhere.couple.CoupleCodeDTO">
    SELECT user_id, code, updated_at
    FROM couple_code
    WHERE user_id = #{userId}
  </select>

  <select id="findByCode" parameterType="String" resultType="com.playhere.couple.CoupleCodeDTO">
    SELECT user_id, code, updated_at
    FROM couple_code
    WHERE code = #{code}
  </select>

  <insert id="insertCoupleCode" parameterType="com.playhere.couple.CoupleCodeDTO">
    INSERT INTO couple_code (user_id, code, updated_at)
    VALUES (#{userId}, #{code}, #{updatedAt})
  </insert>

  <update id="updateCoupleCode" parameterType="com.playhere.couple.CoupleCodeDTO">
    UPDATE couple_code
    SET code = #{code}, updated_at = #{updatedAt}
    WHERE user_id = #{userId}
  </update>

  <select id="findAllUserIds" resultType="String">
    SELECT user_id FROM couple_code
  </select>

</mapper>